russianpodcast/__init__.py
russianpodcast/get_episodes.py
russianpodcast/russianpodcast.py
russianpodcast-0.1.2.dist-info/AUTHORS
russianpodcast-0.1.2.dist-info/AUTHORS.rst
russianpodcast-0.1.2.dist-info/LICENSE
russianpodcast-0.1.2.dist-info/METADATA
russianpodcast-0.1.2.dist-info/WHEEL
russianpodcast-0.1.2.dist-info/entry_points.txt
russianpodcast-0.1.2.dist-info/pbr.json
russianpodcast-0.1.2.dist-info/top_level.txt
russianpodcast-0.1.2.dist-info/RECORD
