Metadata-Version: 2.1
Name: russianpodcast
Version: 0.1.2
Summary: Fetches podcasts from russianpodcast.eu automatically
Home-page: https://github.com/cgte/russianpodcast
Author: Colin G
Author-email: cgte@bk.ru
License: GNU General Public License v3
Keywords: russianpodcast
Platform: UNKNOWN
Classifier: Development Status :: 2 - Pre-Alpha
Classifier: Intended Audience :: Developers
Classifier: License :: OSI Approved :: GNU General Public License v3 (GPLv3)
Classifier: Natural Language :: English
Classifier: Programming Language :: Python :: 2
Classifier: Programming Language :: Python :: 2.7
Classifier: Programming Language :: Python :: 3
Classifier: Programming Language :: Python :: 3.4
Classifier: Programming Language :: Python :: 3.5
Classifier: Programming Language :: Python :: 3.6
Classifier: Programming Language :: Python :: 3.7
Requires-Dist: requests
Requires-Dist: beautifulsoup4
Requires-Dist: selenium
